cudo_compute_sdk/__init__.py
cudo_compute_sdk/schema.py
cudo_compute_sdk-0.0.3.dist-info/METADATA
cudo_compute_sdk-0.0.3.dist-info/WHEEL
cudo_compute_sdk-0.0.3.dist-info/licenses/LICENSE
cudo_compute_sdk-0.0.3.dist-info/RECORD
