Metadata-Version: 2.4
Name: cudo-compute-sdk
Version: 0.0.3
Summary: The Python SDK for Cudo Compute distributed compute platform.
Author-email: jamesbeedy <james@vantagecompute.ai>
License: Apache-2.0
License-File: LICENSE
Requires-Python: >=3.12
Requires-Dist: httpx>=0.28.1
Requires-Dist: pydantic>=2.0.0
Provides-Extra: dev
Requires-Dist: black; extra == 'dev'
Requires-Dist: codespell; extra == 'dev'
Requires-Dist: coverage[toml]~=7.8; extra == 'dev'
Requires-Dist: pyright; extra == 'dev'
Requires-Dist: pytest-asyncio>=0.21.0; extra == 'dev'
Requires-Dist: pytest>=7.0.0; extra == 'dev'
Requires-Dist: ruff; extra == 'dev'
